3_stopwatch/src/seven_seg_controller.v
`timescale 1ns / 1ps

module seven_seg_controller(
    input  wire       clk_mux,    // ~500 Hz multiplexing clock
    input  wire       rst,
    input  wire [3:0] digit3,     // leftmost digit (minutes tens)
    input  wire [3:0] digit2,     // minutes ones
    input  wire [3:0] digit1,     // seconds tens
    input  wire [3:0] digit0,     // rightmost digit (seconds ones)
    input  wire       blank_min,  // blank minutes digits (for blink)
    input  wire       blank_sec,  // blank seconds digits (for blink)
    output reg  [6:0] seg,        // segment outputs (active low)
    output reg  [3:0] an          // anode outputs (active low)
);

    reg [1:0] sel;  // which digit is currently active
    reg [3:0] current_digit;
    reg       blank_current;

    initial sel = 0;

    // Cycle through 4 digits
    always @(posedge clk_mux or posedge rst) begin
        if (rst)
            sel <= 0;
        else
            sel <= sel + 1;
    end

    // Select current digit and blank signal
    always @(*) begin
        case (sel)
            2'b00: begin
                current_digit = digit0;
                an = 4'b1110;
                blank_current = blank_sec;
            end
            2'b01: begin
                current_digit = digit1;
                an = 4'b1101;
                blank_current = blank_sec;
            end
            2'b10: begin
                current_digit = digit2;
                an = 4'b1011;
                blank_current = blank_min;
            end
            2'b11: begin
                current_digit = digit3;
                an = 4'b0111;
                blank_current = blank_min;
            end
        endcase
    end

    // BCD to seven-segment decoder (active low: 0 = segment ON)
    // Segment mapping: seg[6:0] = {g, f, e, d, c, b, a}
    always @(*) begin
        if (blank_current) begin
            seg = 7'b1111111; // all segments off when blanked
        end else begin
            case (current_digit)
                4'd0: seg = 7'b1000000;
                4'd1: seg = 7'b1111001;
                4'd2: seg = 7'b0100100;
                4'd3: seg = 7'b0110000;
                4'd4: seg = 7'b0011001;
                4'd5: seg = 7'b0010010;
                4'd6: seg = 7'b0000010;
                4'd7: seg = 7'b1111000;
                4'd8: seg = 7'b0000000;
                4'd9: seg = 7'b0010000;
                default: seg = 7'b1111111;
            endcase
        end
    end

endmodule

3_stopwatch/src/debouncer.v
`timescale 1ns / 1ps

module debouncer(
    input  wire clk,      // sampling clock (~500 Hz)
    input  wire rst,      // active-high reset
    input  wire noisy_in, // raw button/switch input
    output reg  clean_out // debounced output
);

    // Two flip-flop synchronizer to handle metastability
    reg sync_0, sync_1;

    initial begin
        sync_0 = 0;
        sync_1 = 0;
    end

    always @(posedge clk or posedge rst) begin
        if (rst) begin
            sync_0 <= 0;
            sync_1 <= 0;
        end else begin
            sync_0 <= noisy_in;
            sync_1 <= sync_0;
        end
    end

    // Debounce counter - require stable input for multiple cycles
    reg [3:0] count;
    reg       state;

    initial begin
        count     = 0;
        state     = 0;
        clean_out = 0;
    end

    always @(posedge clk or posedge rst) begin
        if (rst) begin
            count     <= 0;
            state     <= 0;
            clean_out <= 0;
        end else begin
            if (sync_1 == state) begin
                count <= 0;
            end else begin
                count <= count + 1;
                if (count == 4'hF) begin
                    state     <= sync_1;
                    clean_out <= sync_1;
                end
            end
        end
    end

endmodule

3_stopwatch/src/clock_divider.v
`timescale 1ns / 1ps

module clock_divider(
    input  wire clk_100mhz,  // 100 MHz master clock
    input  wire rst,          // active-high reset
    output reg  en_1hz,       // 1-cycle pulse at 1 Hz rate
    output reg  en_2hz,       // 1-cycle pulse at 2 Hz rate
    output reg  clk_500hz,    // ~500 Hz toggle for display mux & debounce
    output reg  clk_blink     // ~4 Hz toggle for blinking in adjust mode
);

    // Full-period counts (pulse once per full period, not half)
    // 100MHz / 1Hz = 100,000,000
    // 100MHz / 2Hz = 50,000,000
    // 100MHz / 500Hz = 200,000 -> toggle at 100,000
    // 100MHz / 4Hz = 25,000,000 -> toggle at 12,500,000

    `ifdef SIMULATION
        localparam CNT_1HZ_MAX   = 100 - 1;   // full period
        localparam CNT_2HZ_MAX   = 50 - 1;    // full period
        localparam CNT_500HZ     = 5 - 1;     // half period (toggle)
        localparam CNT_BLINK     = 12 - 1;    // half period (toggle)
    `else
        localparam CNT_1HZ_MAX   = 100_000_000 - 1;
        localparam CNT_2HZ_MAX   = 50_000_000 - 1;
        localparam CNT_500HZ     = 100_000 - 1;
        localparam CNT_BLINK     = 12_500_000 - 1;
    `endif

    reg [26:0] counter_1hz;
    reg [25:0] counter_2hz;
    reg [16:0] counter_500hz;
    reg [23:0] counter_blink;

    initial begin
        counter_1hz   = 0;
        counter_2hz   = 0;
        counter_500hz = 0;
        counter_blink = 0;
        en_1hz    = 0;
        en_2hz    = 0;
        clk_500hz = 0;
        clk_blink = 0;
    end

    // 1 Hz enable pulse (one master clock cycle wide)
    always @(posedge clk_100mhz or posedge rst) begin
        if (rst) begin
            counter_1hz <= 0;
            en_1hz <= 0;
        end else if (counter_1hz == CNT_1HZ_MAX) begin
            counter_1hz <= 0;
            en_1hz <= 1;
        end else begin
            counter_1hz <= counter_1hz + 1;
            en_1hz <= 0;
        end
    end

    // 2 Hz enable pulse (one master clock cycle wide)
    always @(posedge clk_100mhz or posedge rst) begin
        if (rst) begin
            counter_2hz <= 0;
            en_2hz <= 0;
        end else if (counter_2hz == CNT_2HZ_MAX) begin
            counter_2hz <= 0;
            en_2hz <= 1;
        end else begin
            counter_2hz <= counter_2hz + 1;
            en_2hz <= 0;
        end
    end

    // ~500 Hz toggle (for seven-segment display mux & debounce sampling)
    always @(posedge clk_100mhz or posedge rst) begin
        if (rst) begin
            counter_500hz <= 0;
            clk_500hz <= 0;
        end else if (counter_500hz == CNT_500HZ) begin
            counter_500hz <= 0;
            clk_500hz <= ~clk_500hz;
        end else begin
            counter_500hz <= counter_500hz + 1;
        end
    end

    // ~4 Hz blink toggle
    always @(posedge clk_100mhz or posedge rst) begin
        if (rst) begin
            counter_blink <= 0;
            clk_blink <= 0;
        end else if (counter_blink == CNT_BLINK) begin
            counter_blink <= 0;
            clk_blink <= ~clk_blink;
        end else begin
            counter_blink <= counter_blink + 1;
        end
    end

endmodule

3_stopwatch/src/stopwatch.v
`timescale 1ns / 1ps

module stopwatch(
    input  wire       clk,    // 100 MHz master clock
    input  wire       btnR,   // RESET button (active high)
    input  wire       btnL,   // PAUSE button (active high)
    input  wire       sw_adj, // ADJ switch
    input  wire       sw_sel, // SEL switch (0=minutes, 1=seconds)
    output wire [6:0] seg,    // seven-segment cathode signals
    output wire [3:0] an      // seven-segment anode signals
);

    // =========================================================
    // Internal wires
    // =========================================================
    wire en_1hz, en_2hz, clk_500hz, clk_blink;
    wire rst_db, pause_db, adj_db, sel_db;

    // =========================================================
    // Clock Divider (enable pulses + toggle clocks)
    // =========================================================
    clock_divider u_clk_div (
        .clk_100mhz (clk),
        .rst         (1'b0),        // free-running
        .en_1hz      (en_1hz),      // 1-cycle pulse at 1Hz
        .en_2hz      (en_2hz),      // 1-cycle pulse at 2Hz
        .clk_500hz   (clk_500hz),   // toggle for display mux & debounce
        .clk_blink   (clk_blink)    // toggle for blink display
    );

    // =========================================================
    // Debouncers (still clocked by 500Hz toggle - fine for sampling)
    // =========================================================
    debouncer u_db_rst (
        .clk       (clk_500hz),
        .rst       (1'b0),
        .noisy_in  (btnR),
        .clean_out (rst_db)
    );

    debouncer u_db_pause (
        .clk       (clk_500hz),
        .rst       (1'b0),
        .noisy_in  (btnL),
        .clean_out (pause_db)
    );

    debouncer u_db_adj (
        .clk       (clk_500hz),
        .rst       (1'b0),
        .noisy_in  (sw_adj),
        .clean_out (adj_db)
    );

    debouncer u_db_sel (
        .clk       (clk_500hz),
        .rst       (1'b0),
        .noisy_in  (sw_sel),
        .clean_out (sel_db)
    );

    // =========================================================
    // Pause Toggle Logic (master clock domain)
    // =========================================================
    reg paused;
    reg pause_prev;

    initial begin
        paused     = 0;
        pause_prev = 0;
    end

    always @(posedge clk) begin
        if (rst_db) begin
            paused     <= 0;
            pause_prev <= 0;
        end else begin
            pause_prev <= pause_db;
            // Rising edge detection on debounced pause button
            if (pause_db && !pause_prev)
                paused <= ~paused;
        end
    end

    // =========================================================
    // Time Counters (master clock domain, using enable pulses)
    // =========================================================
    reg [5:0] sec_count;  // 0-59 seconds
    reg [5:0] min_count;  // 0-59 minutes

    initial begin
        sec_count = 0;
        min_count = 0;
    end

    always @(posedge clk) begin
        if (rst_db) begin
            sec_count <= 0;
            min_count <= 0;
        end else if (adj_db) begin
            // ---- Adjustment Mode ----
            if (en_2hz) begin
                if (sel_db) begin
                    // SEL=1: increment seconds
                    if (sec_count == 59)
                        sec_count <= 0;
                    else
                        sec_count <= sec_count + 1;
                end else begin
                    // SEL=0: increment minutes
                    if (min_count == 59)
                        min_count <= 0;
                    else
                        min_count <= min_count + 1;
                end
            end
        end else if (!paused) begin
            // ---- Normal Mode ----
            if (en_1hz) begin
                if (sec_count == 59) begin
                    sec_count <= 0;
                    if (min_count == 59)
                        min_count <= 0;
                    else
                        min_count <= min_count + 1;
                end else begin
                    sec_count <= sec_count + 1;
                end
            end
        end
    end

    // =========================================================
    // BCD Digit Extraction
    // =========================================================
    wire [3:0] sec_ones = sec_count % 10;
    wire [3:0] sec_tens = sec_count / 10;
    wire [3:0] min_ones = min_count % 10;
    wire [3:0] min_tens = min_count / 10;

    // =========================================================
    // Blink Logic for Adjustment Mode
    // =========================================================
    wire blank_min = adj_db && !sel_db && clk_blink;
    wire blank_sec = adj_db &&  sel_db && clk_blink;

    // =========================================================
    // Seven-Segment Display Controller
    // =========================================================
    seven_seg_controller u_display (
        .clk_mux   (clk_500hz),
        .rst       (rst_db),
        .digit3    (min_tens),
        .digit2    (min_ones),
        .digit1    (sec_tens),
        .digit0    (sec_ones),
        .blank_min (blank_min),
        .blank_sec (blank_sec),
        .seg       (seg),
        .an        (an)
    );

endmodule

3_stopwatch/sim/stopwatch_tb.v
`timescale 1ns / 1ps

module stopwatch_tb;

    // =========================================================
    // Signals
    // =========================================================
    reg        clk;
    reg        btnR;    // RESET
    reg        btnL;    // PAUSE
    reg        sw_adj;  // ADJ switch
    reg        sw_sel;  // SEL switch
    wire [6:0] seg;
    wire [3:0] an;

    // =========================================================
    // DUT Instantiation
    // =========================================================
    stopwatch uut (
        .clk    (clk),
        .btnR   (btnR),
        .btnL   (btnL),
        .sw_adj (sw_adj),
        .sw_sel (sw_sel),
        .seg    (seg),
        .an     (an)
    );

    // =========================================================
    // Clock Generation (100 MHz -> 10ns period)
    // =========================================================
    initial clk = 0;
    always #5 clk = ~clk;

    // =========================================================
    // Internal signal access
    // =========================================================
    wire [5:0] sec_val = uut.sec_count;
    wire [5:0] min_val = uut.min_count;
    wire       paused_val = uut.paused;

    // =========================================================
    // Timing helpers
    // With SIMULATION dividers (CNT_1HZ=49, CNT_500HZ=4):
    //   clk_500hz period = 2 * 5 * 10ns = 100ns
    //   clk_1hz period   = 2 * 50 * 100ns = 10,000ns = 10us
    //   clk_2hz period   = 2 * 25 * 100ns = 5,000ns  = 5us
    //   debounce settle  = 16 * 100ns = 1,600ns ~ 2us
    // =========================================================
    // With SIMULATION dividers:
    //   en_1hz fires every 100 master clocks = 1000ns (1 per sim second)
    //   en_2hz fires every 50  master clocks = 500ns  (2 per sim second)
    //   clk_500hz period = 2 * 5 * 10ns = 100ns
    //   debounce = 18 cycles of clk_500hz = 1800ns
    //
    // NOTE: debounce_settle itself costs ~2 simulated seconds,
    //       so timing-sensitive checks must account for that.

    task wait_seconds;
        input integer n;
        begin
            #(n * 1_000);  // 1 sim "second" = 1000ns = 1us
        end
    endtask

    task debounce_settle;
        begin
            #2_000;  // 2us > 1.6us debounce time (~2 sim seconds)
        end
    endtask

    // =========================================================
    // Pass/fail tracking
    // =========================================================
    integer pass_count = 0;
    integer fail_count = 0;

    task check_exact;
        input [255:0] name;
        input integer exp_min, exp_sec, exp_paused;
        begin
            if (min_val === exp_min[5:0] &&
                sec_val === exp_sec[5:0] &&
                paused_val === exp_paused[0]) begin
                $display("  PASS: %0s | min=%0d sec=%0d paused=%0b",
                         name, min_val, sec_val, paused_val);
                pass_count = pass_count + 1;
            end else begin
                $display("  FAIL: %0s | expected min=%0d sec=%0d paused=%0b | got min=%0d sec=%0d paused=%0b",
                         name, exp_min, exp_sec, exp_paused,
                         min_val, sec_val, paused_val);
                fail_count = fail_count + 1;
            end
        end
    endtask

    task check_range;
        input [255:0] name;
        input integer min_lo, min_hi, sec_lo, sec_hi;
        begin
            if (min_val >= min_lo[5:0] && min_val <= min_hi[5:0] &&
                sec_val >= sec_lo[5:0] && sec_val <= sec_hi[5:0]) begin
                $display("  PASS: %0s | min=%0d sec=%0d (in range)",
                         name, min_val, sec_val);
                pass_count = pass_count + 1;
            end else begin
                $display("  FAIL: %0s | min=%0d sec=%0d not in min=[%0d,%0d] sec=[%0d,%0d]",
                         name, min_val, sec_val,
                         min_lo, min_hi, sec_lo, sec_hi);
                fail_count = fail_count + 1;
            end
        end
    endtask

    task check_true;
        input [255:0] name;
        input condition;
        begin
            if (condition) begin
                $display("  PASS: %0s | min=%0d sec=%0d paused=%0b",
                         name, min_val, sec_val, paused_val);
                pass_count = pass_count + 1;
            end else begin
                $display("  FAIL: %0s | min=%0d sec=%0d paused=%0b",
                         name, min_val, sec_val, paused_val);
                fail_count = fail_count + 1;
            end
        end
    endtask

    // =========================================================
    // Test Stimulus
    // =========================================================
    reg [5:0] saved_min, saved_sec;

    initial begin
        $dumpfile("stopwatch_tb.vcd");
        $dumpvars(0, stopwatch_tb);

        btnR = 0; btnL = 0; sw_adj = 0; sw_sel = 0;

        $display("");
        $display("========================================");
        $display("  Stopwatch Testbench");
        $display("========================================");

        // ---- Test 1: Reset ----
        $display("");
        $display("[Test 1] Reset");
        btnR = 1;
        debounce_settle;
        check_exact("Counters zeroed while reset held", 0, 0, 0);
        btnR = 0;
        debounce_settle;

        // ---- Test 2: Normal counting ----
        $display("");
        $display("[Test 2] Normal Counting");
        wait_seconds(5);
        check_range("~5 seconds elapsed", 0, 0, 3, 7);
        wait_seconds(5);
        check_range("~10 seconds elapsed", 0, 0, 8, 12);

        // ---- Test 3: Pause ----
        $display("");
        $display("[Test 3] Pause");
        btnL = 1;
        debounce_settle;
        btnL = 0;
        debounce_settle;
        // Now paused - save position AFTER pause takes effect
        saved_min = min_val;
        saved_sec = sec_val;
        wait_seconds(10);
        check_true("Counter frozen while paused",
                   (sec_val == saved_sec) && (min_val == saved_min));

        // ---- Test 4: Unpause ----
        $display("");
        $display("[Test 4] Unpause");
        saved_sec = sec_val;
        saved_min = min_val;
        btnL = 1;
        debounce_settle;
        btnL = 0;
        debounce_settle;
        wait_seconds(5);
        check_true("Counter resumed after unpause",
                   (sec_val > saved_sec) || (min_val > saved_min));

        // ---- Test 5: Reset to prepare for adjust ----
        $display("");
        $display("[Test 5] Reset before adjust tests");
        btnR = 1;
        debounce_settle;
        check_exact("Reset to 00:00", 0, 0, 0);
        btnR = 0;
        debounce_settle;

        // ---- Test 6: Adjust seconds (SEL=1) ----
        $display("");
        $display("[Test 6] Adjust Seconds (ADJ=1, SEL=1)");
        sw_adj = 1;
        sw_sel = 1;
        debounce_settle;
        wait_seconds(10);
        // 2Hz tick = every ~500ns sim time
        check_true("Seconds incrementing via 2Hz", sec_val > 0);
        check_true("Minutes still zero", min_val == 0);

        // ---- Test 7: Adjust minutes (SEL=0) ----
        $display("");
        $display("[Test 7] Adjust Minutes (ADJ=1, SEL=0)");
        sw_sel = 0;
        debounce_settle;
        // Save sec AFTER sel debounce settles so ticks go to minutes
        saved_sec = sec_val;
        wait_seconds(20);
        check_true("Minutes incrementing via 2Hz", min_val > 0);
        check_true("Seconds frozen during min adjust", sec_val == saved_sec);

        // ---- Test 8: Exit adjust -> normal ----
        $display("");
        $display("[Test 8] Exit Adjust -> Normal Mode");
        saved_min = min_val;
        saved_sec = sec_val;
        sw_adj = 0;
        debounce_settle;
        wait_seconds(5);
        check_true("Normal counting resumed",
                   (sec_val != saved_sec) || (min_val != saved_min));

        // ---- Test 9: Rollover (59->0 seconds, minute increment) ----
        $display("");
        $display("[Test 9] Second Rollover 59->0");
        btnR = 1;
        debounce_settle;
        btnR = 0;
        debounce_settle;
        // Run in normal mode long enough to guarantee rollover (>60 sim seconds)
        wait_seconds(62);
        check_true("Seconds rolled over, minutes incremented", min_val >= 1);

        // ---- Test 10: Final reset ----
        $display("");
        $display("[Test 10] Final Reset");
        btnR = 1;
        debounce_settle;
        check_exact("All counters zeroed", 0, 0, 0);
        btnR = 0;
        debounce_settle;

        // ---- Summary ----
        $display("");
        $display("========================================");
        $display("  %0d PASSED, %0d FAILED", pass_count, fail_count);
        if (fail_count == 0)
            $display("  ALL TESTS PASSED");
        else
            $display("  SOME TESTS FAILED");
        $display("========================================");
        $display("");

        $finish;
    end

endmodule

3_stopwatch/stopwatch_tb.vcd
$date
	Mon Feb  9 11:56:53 2026
$end
$version
	Icarus Verilog
$end
$timescale
	1ps
$end
$scope module stopwatch_tb $end
$var wire 6 ! min_val [5:0] $end
$var wire 1 " paused_val $end
$var wire 6 # sec_val [5:0] $end
$var wire 7 $ seg [6:0] $end
$var wire 4 % an [3:0] $end
$var reg 1 & btnL $end
$var reg 1 ' btnR $end
$var reg 1 ( clk $end
$var reg 6 ) saved_min [5:0] $end
$var reg 6 * saved_sec [5:0] $end
$var reg 1 + sw_adj $end
$var reg 1 , sw_sel $end
$var integer 32 - fail_count [31:0] $end
$var integer 32 . pass_count [31:0] $end
$scope module uut $end
$var wire 1 / blank_min $end
$var wire 1 0 blank_sec $end
$var wire 1 & btnL $end
$var wire 1 ' btnR $end
$var wire 1 ( clk $end
$var wire 1 + sw_adj $end
$var wire 1 , sw_sel $end
$var wire 1 1 sel_db $end
$var wire 7 2 seg [6:0] $end
$var wire 4 3 sec_tens [3:0] $end
$var wire 4 4 sec_ones [3:0] $end
$var wire 1 5 rst_db $end
$var wire 1 6 pause_db $end
$var wire 4 7 min_tens [3:0] $end
$var wire 4 8 min_ones [3:0] $end
$var wire 1 9 en_2hz $end
$var wire 1 : en_1hz $end
$var wire 1 ; clk_blink $end
$var wire 1 < clk_500hz $end
$var wire 4 = an [3:0] $end
$var wire 1 > adj_db $end
$var reg 6 ? min_count [5:0] $end
$var reg 1 @ pause_prev $end
$var reg 1 A paused $end
$var reg 6 B sec_count [5:0] $end
$scope module u_clk_div $end
$var wire 1 ( clk_100mhz $end
$var wire 1 C rst $end
$var parameter 33 D CNT_1HZ_MAX $end
$var parameter 33 E CNT_2HZ_MAX $end
$var parameter 33 F CNT_500HZ $end
$var parameter 33 G CNT_BLINK $end
$var reg 1 < clk_500hz $end
$var reg 1 ; clk_blink $end
$var reg 27 H counter_1hz [26:0] $end
$var reg 26 I counter_2hz [25:0] $end
$var reg 17 J counter_500hz [16:0] $end
$var reg 24 K counter_blink [23:0] $end
$var reg 1 : en_1hz $end
$var reg 1 9 en_2hz $end
$upscope $end
$scope module u_db_adj $end
$var wire 1 < clk $end
$var wire 1 + noisy_in $end
$var wire 1 L rst $end
$var reg 1 > clean_out $end
$var reg 4 M count [3:0] $end
$var reg 1 N state $end
$var reg 1 O sync_0 $end
$var reg 1 P sync_1 $end
$upscope $end
$scope module u_db_pause $end
$var wire 1 < clk $end
$var wire 1 & noisy_in $end
$var wire 1 Q rst $end
$var reg 1 6 clean_out $end
$var reg 4 R count [3:0] $end
$var reg 1 S state $end
$var reg 1 T sync_0 $end
$var reg 1 U sync_1 $end
$upscope $end
$scope module u_db_rst $end
$var wire 1 < clk $end
$var wire 1 ' noisy_in $end
$var wire 1 V rst $end
$var reg 1 5 clean_out $end
$var reg 4 W count [3:0] $end
$var reg 1 X state $end
$var reg 1 Y sync_0 $end
$var reg 1 Z sync_1 $end
$upscope $end
$scope module u_db_sel $end
$var wire 1 < clk $end
$var wire 1 , noisy_in $end
$var wire 1 [ rst $end
$var reg 1 1 clean_out $end
$var reg 4 \ count [3:0] $end
$var reg 1 ] state $end
$var reg 1 ^ sync_0 $end
$var reg 1 _ sync_1 $end
$upscope $end
$scope module u_display $end
$var wire 1 / blank_min $end
$var wire 1 0 blank_sec $end
$var wire 1 < clk_mux $end
$var wire 4 ` digit0 [3:0] $end
$var wire 4 a digit1 [3:0] $end
$var wire 4 b digit2 [3:0] $end
$var wire 4 c digit3 [3:0] $end
$var wire 1 5 rst $end
$var reg 4 d an [3:0] $end
$var reg 1 e blank_current $end
$var reg 4 f current_digit [3:0] $end
$var reg 7 g seg [6:0] $end
$var reg 2 h sel [1:0] $end
$upscope $end
$upscope $end
$scope task check_exact $end
$var reg 256 i name [255:0] $end
$var integer 32 j exp_min [31:0] $end
$var integer 32 k exp_paused [31:0] $end
$var integer 32 l exp_sec [31:0] $end
$upscope $end
$scope task check_range $end
$var reg 256 m name [255:0] $end
$var integer 32 n min_hi [31:0] $end
$var integer 32 o min_lo [31:0] $end
$var integer 32 p sec_hi [31:0] $end
$var integer 32 q sec_lo [31:0] $end
$upscope $end
$scope task check_true $end
$var reg 1 r condition $end
$var reg 256 s name [255:0] $end
$upscope $end
$scope task debounce_settle $end
$upscope $end
$scope task wait_seconds $end
$var integer 32 t n [31:0] $end
$upscope $end
$upscope $end
$enddefinitions $end
$comment Show the parameter values. $end
$dumpall
b1011 G
b100 F
b110001 E
b1100011 D
$end
#0
$dumpvars
bx t
bx s
xr
bx q
bx p
bx o
bx n
bx m
bx l
bx k
bx j
bx i
b0 h
b1000000 g
b0 f
0e
b1110 d
b0 c
b0 b
b0 a
b0 `
0_
0^
0]
b0 \
0[
0Z
0Y
0X
b0 W
0V
0U
0T
0S
b0 R
0Q
0P
0O
0N
b0 M
0L
b0 K
b0 J
b0 I
b0 H
0C
b0 B
0A
0@
b0 ?
0>
b1110 =
0<
0;
0:
09
b0 8
b0 7
06
05
b0 4
b0 3
b1000000 2
01
00
0/
b0 .
b0 -
0,
0+
bx *
bx )
0(
1'
0&
b1110 %
b1000000 $
b0 #
0"
b0 !
$end
#5000
b1 H
b1 I
b1 J
b1 K
1(
#10000
0(
#15000
b10 K
b10 J
b10 I
b10 H
1(
#20000
0(
#25000
b11 H
b11 I
b11 J
b11 K
1(
#30000
0(
#35000
b100 K
b100 J
b100 I
b100 H
1(
#40000
0(
#45000
b1101 %
b1101 =
b1101 d
1Y
b1 h
b101 H
b101 I
1<
b0 J
b101 K
1(
#50000
0(
#55000
b110 K
b1 J
b110 I
b110 H
1(
#60000
0(
#65000
b111 H
b111 I
b10 J
b111 K
1(
#70000
0(
#75000
b1000 K
b11 J
b1000 I
b1000 H
1(
#80000
0(
#85000
b1001 H
b1001 I
b100 J
b1001 K
1(
#90000
0(
#95000
b1010 K
0<
b0 J
b1010 I
b1010 H
1(
#100000
0(
#105000
b1011 H
b1011 I
b1 J
b1011 K
1(
#110000
0(
#115000
1;
b0 K
b10 J
b1100 I
b1100 H
1(
#120000
0(
#125000
b1101 H
b1101 I
b11 J
b1 K
1(
#130000
0(
#135000
b10 K
b100 J
b1110 I
b1110 H
1(
#140000
0(
#145000
b1011 %
b1011 =
b1011 d
1Z
b10 h
b1111 H
b1111 I
1<
b0 J
b11 K
1(
#150000
0(
#155000
b100 K
b1 J
b10000 I
b10000 H
1(
#160000
0(
#165000
b10001 H
b10001 I
b10 J
b101 K
1(
#170000
0(
#175000
b110 K
b11 J
b10010 I
b10010 H
1(
#180000
0(
#185000
b10011 H
b10011 I
b100 J
b111 K
1(
#190000
0(
#195000
b1000 K
0<
b0 J
b10100 I
b10100 H
1(
#200000
0(
#205000
b10101 H
b10101 I
b1 J
b1001 K
1(
#210000
0(
#215000
b1010 K
b10 J
b10110 I
b10110 H
1(
#220000
0(
#225000
b10111 H
b10111 I
b11 J
b1011 K
1(
#230000
0(
#235000
0;
b0 K
b100 J
b11000 I
b11000 H
1(
#240000
0(
#245000
b111 %
b111 =
b111 d
b1 W
b11 h
b11001 H
b11001 I
1<
b0 J
b1 K
1(
#250000
0(
#255000
b10 K
b1 J
b11010 I
b11010 H
1(
#260000
0(
#265000
b11011 H
b11011 I
b10 J
b11 K
1(
#270000
0(
#275000
b100 K
b11 J
b11100 I
b11100 H
1(
#280000
0(
#285000
b11101 H
b11101 I
b100 J
b101 K
1(
#290000
0(
#295000
b110 K
0<
b0 J
b11110 I
b11110 H
1(
#300000
0(
#305000
b11111 H
b11111 I
b1 J
b111 K
1(
#310000
0(
#315000
b1000 K
b10 J
b100000 I
b100000 H
1(
#320000
0(
#325000
b100001 H
b100001 I
b11 J
b1001 K
1(
#330000
0(
#335000
b1010 K
b100 J
b100010 I
b100010 H
1(
#340000
0(
#345000
b1110 %
b1110 =
b1110 d
b10 W
b0 h
b100011 H
b100011 I
1<
b0 J
b1011 K
1(
#350000
0(
#355000
1;
b0 K
b1 J
b100100 I
b100100 H
1(
#360000
0(
#365000
b100101 H
b100101 I
b10 J
b1 K
1(
#370000
0(
#375000
b10 K
b11 J
b100110 I
b100110 H
1(
#380000
0(
#385000
b100111 H
b100111 I
b100 J
b11 K
1(
#390000
0(
#395000
b100 K
0<
b0 J
b101000 I
b101000 H
1(
#400000
0(
#405000
b101001 H
b101001 I
b1 J
b101 K
1(
#410000
0(
#415000
b110 K
b10 J
b101010 I
b101010 H
1(
#420000
0(
#425000
b101011 H
b101011 I
b11 J
b111 K
1(
#430000
0(
#435000
b1000 K
b100 J
b101100 I
b101100 H
1(
#440000
0(
#445000
b1101 %
b1101 =
b1101 d
b11 W
b1 h
b101101 H
b101101 I
1<
b0 J
b1001 K
1(
#450000
0(
#455000
b1010 K
b1 J
b101110 I
b101110 H
1(
#460000
0(
#465000
b101111 H
b101111 I
b10 J
b1011 K
1(
#470000
0(
#475000
0;
b0 K
b11 J
b110000 I
b110000 H
1(
#480000
0(
#485000
b110001 H
b110001 I
b100 J
b1 K
1(
#490000
0(
#495000
b10 K
0<
b0 J
19
b0 I
b110010 H
1(
#500000
0(
#505000
b110011 H
09
b1 I
b1 J
b11 K
1(
#510000
0(
#515000
b100 K
b10 J
b10 I
b110100 H
1(
#520000
0(
#525000
b110101 H
b11 I
b11 J
b101 K
1(
#530000
0(
#535000
b110 K
b100 J
b100 I
b110110 H
1(
#540000
0(
#545000
b1011 %
b1011 =
b1011 d
b100 W
b10 h
b110111 H
b101 I
1<
b0 J
b111 K
1(
#550000
0(
#555000
b1000 K
b1 J
b110 I
b111000 H
1(
#560000
0(
#565000
b111001 H
b111 I
b10 J
b1001 K
1(
#570000
0(
#575000
b1010 K
b11 J
b1000 I
b111010 H
1(
#580000
0(
#585000
b111011 H
b1001 I
b100 J
b1011 K
1(
#590000
0(
#595000
1;
b0 K
0<
b0 J
b1010 I
b111100 H
1(
#600000
0(
#605000
b111101 H
b1011 I
b1 J
b1 K
1(
#610000
0(
#615000
b10 K
b10 J
b1100 I
b111110 H
1(
#620000
0(
#625000
b111111 H
b1101 I
b11 J
b11 K
1(
#630000
0(
#635000
b100 K
b100 J
b1110 I
b1000000 H
1(
#640000
0(
#645000
b111 %
b111 =
b111 d
b101 W
b11 h
b1000001 H
b1111 I
1<
b0 J
b101 K
1(
#650000
0(
#655000
b110 K
b1 J
b10000 I
b1000010 H
1(
#660000
0(
#665000
b1000011 H
b10001 I
b10 J
b111 K
1(
#670000
0(
#675000
b1000 K
b11 J
b10010 I
b1000100 H
1(
#680000
0(
#685000
b1000101 H
b10011 I
b100 J
b1001 K
1(
#690000
0(
#695000
b1010 K
0<
b0 J
b10100 I
b1000110 H
1(
#700000
0(
#705000
b1000111 H
b10101 I
b1 J
b1011 K
1(
#710000
0(
#715000
0;
b0 K
b10 J
b10110 I
b1001000 H
1(
#720000
0(
#725000
b1001001 H
b10111 I
b11 J
b1 K
1(
#730000
0(
#735000
b10 K
b100 J
b11000 I
b1001010 H
1(
#740000
0(
#745000
b1110 %
b1110 =
b1110 d
b110 W
b0 h
b1001011 H
b11001 I
1<
b0 J
b11 K
1(
#750000
0(
#755000
b100 K
b1 J
b11010 I
b1001100 H
1(
#760000
0(
#765000
b1001101 H
b11011 I
b10 J
b101 K
1(
#770000
0(
#775000
b110 K
b11 J
b11100 I
b1001110 H
1(
#780000
0(
#785000
b1001111 H
b11101 I
b100 J
b111 K
1(
#790000
0(
#795000
b1000 K
0<
b0 J
b11110 I
b1010000 H
1(
#800000
0(
#805000
b1010001 H
b11111 I
b1 J
b1001 K
1(
#810000
0(
#815000
b1010 K
b10 J
b100000 I
b1010010 H
1(
#820000
0(
#825000
b1010011 H
b100001 I
b11 J
b1011 K
1(
#830000
0(
#835000
1;
b0 K
b100 J
b100010 I
b1010100 H
1(
#840000
0(
#845000
b1101 %
b1101 =
b1101 d
b111 W
b1 h
b1010101 H
b100011 I
1<
b0 J
b1 K
1(
#850000
0(
#855000
b10 K
b1 J
b100100 I
b1010110 H
1(
#860000
0(
#865000
b1010111 H
b100101 I
b10 J
b11 K
1(
#870000
0(
#875000
b100 K
b11 J
b100110 I
b1011000 H
1(
#880000
0(
#885000
b1011001 H
b100111 I
b100 J
b101 K
1(
#890000
0(
#895000
b110 K
0<
b0 J
b101000 I
b1011010 H
1(
#900000
0(
#905000
b1011011 H
b101001 I
b1 J
b111 K
1(
#910000
0(
#915000
b1000 K
b10 J
b101010 I
b1011100 H
1(
#920000
0(
#925000
b1011101 H
b101011 I
b11 J
b1001 K
1(
#930000
0(
#935000
b1010 K
b100 J
b101100 I
b1011110 H
1(
#940000
0(
#945000
b1011 %
b1011 =
b1011 d
b1000 W
b10 h
b1011111 H
b101101 I
1<
b0 J
b1011 K
1(
#950000
0(
#955000
0;
b0 K
b1 J
b101110 I
b1100000 H
1(
#960000
0(
#965000
b1100001 H
b101111 I
b10 J
b1 K
1(
#970000
0(
#975000
b10 K
b11 J
b110000 I
b1100010 H
1(
#980000
0(
#985000
b1100011 H
b110001 I
b100 J
b11 K
1(
#990000
0(
#995000
b100 K
0<
b0 J
19
b0 I
1:
b0 H
1(
#1000000
0(
